polls/__init__.py
polls/admin.py
polls/apps.py
polls/models.py
polls/tests.py
polls/urls.py
polls/views.py
polls/migrations/0001_initial.py
polls/migrations/__init__.py
polls/static/polls/style.css
polls/static/polls/images/panda.jpg
polls/templates/polls/detail.html
polls/templates/polls/index.html
polls/templates/polls/results.html
helen_django_polls-0.1.dist-info/METADATA
helen_django_polls-0.1.dist-info/WHEEL
helen_django_polls-0.1.dist-info/top_level.txt
helen_django_polls-0.1.dist-info/RECORD
